LICENSE
MANIFEST.in
README.md
setup.py
getname/__init__.py
getname/cli.py
getname/main.py
getname.egg-info/PKG-INFO
getname.egg-info/SOURCES.txt
getname.egg-info/dependency_links.txt
getname.egg-info/entry_points.txt
getname.egg-info/requires.txt
getname.egg-info/top_level.txt
getname/data/cat_names.json
getname/data/dog_names.json
getname/data/superhero_names.json
getname/data/supervillain_names.json