Metadata-Version: 1.1
Name: getname
Version: 0.1.1
Summary: Get popular cat/dog/superhero/supervillain names
Home-page: http://github.com/lord63/getname
Author: lord63
Author-email: lord63.j@gmail.com
License: MIT
Keywords: name cat dog superhero supervillain
Platform: UNKNOWN
Classifier: Development Status :: 4 - Beta
Classifier: Operating System :: POSIX
Classifier: Operating System :: POSIX :: Linux
Classifier: License :: OSI Approved :: MIT License
Classifier: Programming Language :: Python :: 2
Classifier: Programming Language :: Python :: 2.7
Classifier: Programming Language :: Python :: 3
Classifier: Programming Language :: Python :: 3.3
Classifier: Programming Language :: Python :: 3.4
